{
  "message": ["message:"],
  "help": ["hello", "hi", "hey", "help"],
  "hours": ["open", "close", "closed", "hours"],
  "general": ["when", "event", "events", "happen", "happening", "find", "can i", "do i", "job"],
  "next_month": ["next month"],
  "this_month": ["month", "week"],
  "all_events": ["all", "semester", "year"],
  "next_event": ["next event"],
  "on_campus_jobs": { "keys": ["oncampus", "on-campus", "on campus"], "name": ["How To Find a Job on Campus Workshop", "How To Find a Job on Campus Job Fair"] },
  "international": {"keys": ["international"], "name": ["Job Search Tips for International Students Workshop", "Job Search Tips for International Students Panel"]},
  "tech_fest": { "keys": ["techfest", "tech fest", "engineering", "technology", "engineer"], "name": ["Fall Tech Fest"] },
  "resu_makeover": {"keys": ["resumania", "resu-makeover", "resume makeover", "resume-makeover", "resume critique", "resume", "network", "networking", "prep", "preparation"], "name": ["Resu-Makeover"]},
  "sixty_seconds_to_success": {"keys": ["60", "sixty", "minute", "min", "mock interview", "practice interview", "network", "networking", "prep", "preparation"], "name": ["60 Seconds to Success"]},
  "general_career_fair": {"keys": ["internship", "career", "fair", "grad", "graduate", "alum", "alumni", "network", "networking", "prep", "preparation"], "name": ["Recent Graduate & Alumni Fair"]},
  "non_profit_gov_career_fair": {"keys": ["non-profit", "nonprofit", "government", "gov"], "name": ["Non-Profit & Government Career Fair"]},
  "education_career_fair": {"keys": ["education", "teacher", "teaching", "teach"], "name": ["Education Expo"]},
  "alumni_career_fair": {"keys": ["grad", "graduate", "alum", "alumni", "network", "networking"], "name": ["Recent Graduate & Alumni Fair"]},
  "grad_school": {"keys": ["grad school", "graduate school", "masters", "phd", "doctorate"], "name": ["Graduate School Info Day"]},
  "sunlink": ["sunlink", "password"],
  "location": ["located", "location"]
}
